CloudOrchestrator/__init__.py
CloudOrchestrator/aws_configure.py
CloudOrchestrator/cloudwatch.py
CloudOrchestrator/config.py
CloudOrchestrator/deploy.py
CloudOrchestrator/deploy_algorithm.py
CloudOrchestrator/docker.py
CloudOrchestrator/dynamodb.py
CloudOrchestrator/ec2.py
CloudOrchestrator/ecr.py
CloudOrchestrator/elb.py
CloudOrchestrator/iam.py
CloudOrchestrator/main.py
CloudOrchestrator/populate_instances.py
CloudOrchestrator/rds.py
CloudOrchestrator/route53.py
CloudOrchestrator/s3.py
CloudOrchestrator/sns.py
CloudOrchestrator/ssh.py
CloudOrchestrator/ssm.py
CloudOrchestrator/tags.py
CloudOrchestrator-1.0.3.dist-info/METADATA
CloudOrchestrator-1.0.3.dist-info/WHEEL
CloudOrchestrator-1.0.3.dist-info/entry_points.txt
CloudOrchestrator-1.0.3.dist-info/top_level.txt
CloudOrchestrator-1.0.3.dist-info/RECORD
