Metadata-Version: 2.1
Name: CloudOrchestrator
Version: 1.0.3
Summary: CLI tool for managing AWS resources
Author: Shweta Jha
Author-email: jshweta208@gmail.com
Classifier: Programming Language :: Python :: 3
Classifier: Operating System :: OS Independent
Requires-Python: >=3.6
Requires-Dist: boto3
Requires-Dist: docker
Requires-Dist: PyYAML
Requires-Dist: paramiko
